ircstyle/__init__.py
ircstyle/colors.py
ircstyle-0.1.5.dist-info/LICENSE
ircstyle-0.1.5.dist-info/METADATA
ircstyle-0.1.5.dist-info/WHEEL
ircstyle-0.1.5.dist-info/top_level.txt
ircstyle-0.1.5.dist-info/RECORD
