Metadata-Version: 2.1
Name: ircstyle
Version: 0.1.5
Summary: Apply and strip formatting from IRC messages
Home-page: https://github.com/impredicative/ircstyle
Author: Ouroboros Chrysopoeia
Author-email: impredicative@users.nomail.github.com
License: MIT
Keywords: irc
Platform: UNKNOWN
Classifier: Programming Language :: Python :: 3.7
Classifier: Programming Language :: Python :: 3.8
Classifier: License :: OSI Approved :: MIT License
Classifier: Intended Audience :: Developers
Classifier: Topic :: Communications :: Chat :: Internet Relay Chat
Classifier: Topic :: Software Development :: Libraries :: Python Modules
Classifier: Topic :: Text Processing
Requires-Python: >=3.7
